prefs/__init__.py
prefs/cli.py
prefs/exceptions.py
prefs/parser/grammar.lark
prefs/parser/parser.py
prefs/prefs.py
prefs/utils.py
prefs-1.0.1.dist-info/entry_points.txt
prefs-1.0.1.dist-info/LICENSE
prefs-1.0.1.dist-info/WHEEL
prefs-1.0.1.dist-info/METADATA
prefs-1.0.1.dist-info/RECORD
