Metadata-Version: 2.1
Name: prefs
Version: 1.0.1
Summary: Store and manage preferences easily.
Home-page: https://patitotective.github.io/PREFS/
License: MIT
Keywords: preferences,settings,prefs
Author: Patitotective
Author-email: cristobalriaga@gmail.com
Requires-Python: >=3.6,<4.0
Classifier: License :: OSI Approved :: MIT License
Classifier: Programming Language :: Python :: 3
Classifier: Programming Language :: Python :: 3.10
Classifier: Programming Language :: Python :: 3.6
Classifier: Programming Language :: Python :: 3.7
Classifier: Programming Language :: Python :: 3.8
Classifier: Programming Language :: Python :: 3.9
Requires-Dist: click (>=8.0.3,<9.0.0)
Requires-Dist: lark (>=1.0.0,<2.0.0)
Project-URL: Bug Tracker, https://github.com/python-poetry/poetry/issues
Project-URL: Changelog, https://patitotective.github.io/PREFS/about/changelog
Project-URL: Documentation, https://patitotective.github.io/PREFS/docs/
Project-URL: Discord Server, https://discord.gg/as85Q4GnR6
Project-URL: Repository, https://github.com/Patitotective/PREFS/
